pynamelix/__init__.py
pynamelix/__main__.py
pynamelix/utils.py
pynamelix-0.1.1.dist-info/LICENSE
pynamelix-0.1.1.dist-info/METADATA
pynamelix-0.1.1.dist-info/WHEEL
pynamelix-0.1.1.dist-info/entry_points.txt
pynamelix-0.1.1.dist-info/top_level.txt
pynamelix-0.1.1.dist-info/RECORD
