Metadata-Version: 2.1
Name: pynamelix
Version: 0.1.1
Summary: API to namelix.com
Home-page: https://github.com/axju/pynamelix
Author: axju
Author-email: moin@axju.de
License: MIT
Platform: UNKNOWN
Classifier: Intended Audience :: Developers
Classifier: Operating System :: OS Independent
Classifier: Programming Language :: Python
Classifier: Programming Language :: Python :: 3.6
Classifier: Programming Language :: Python :: 3.7
Classifier: Programming Language :: Python :: 3.8
Classifier: Programming Language :: Python :: 3.9
Requires-Dist: requests
Requires-Dist: check-pypi-name
